aidbox_logging/__init__.py
aidbox_logging/py.typed
aidbox_logging-0.1.0b1.dist-info/LICENSE.md
aidbox_logging-0.1.0b1.dist-info/WHEEL
aidbox_logging-0.1.0b1.dist-info/METADATA
aidbox_logging-0.1.0b1.dist-info/RECORD
