Metadata-Version: 2.3
Name: aidbox-logging
Version: 0.1.0b1
Summary: Aidbox $loggy python logging
Keywords: aidbox,logging
Author-email: "beda.software" <aidbox-logging-py@beda.software>
Requires-Python: >=3.11
Classifier: Development Status :: 5 - Production/Stable
Classifier: Environment :: Web Environment
Classifier: Intended Audience :: Developers
Classifier: Operating System :: OS Independent
Classifier: Programming Language :: Python
Classifier: Programming Language :: Python :: 3
Classifier: Programming Language :: Python :: 3.11
Classifier: Programming Language :: Python :: 3.12
Classifier: Topic :: Software Development :: Libraries :: Python Modules
Requires-Dist: requests>=2.32.3
Project-URL: documentation, https://github.com/beda-software/aidbox-logging-py#readme
Project-URL: homepage, https://github.com/beda-software/aidbox-logging-py
Project-URL: repository, https://github.com/beda-software/aidbox-logging-py.git
